entry_points_googlepostmasterapi/__init__.py
entry_points_googlepostmasterapi/gpt_dl_all_datas.py
entry_points_googlepostmasterapi/gpt_dl_domain_datas.py
entry_points_googlepostmasterapi/gpt_dl_domains.py
googlepostmasterapi/__init__.py
googlepostmasterapi/datas.py
googlepostmasterapi/gpt.py
googlepostmasterapi/stats.py
googlepostmasterapi/utils.py
gpostmaster_domains_datas-0.0.3.dist-info/LICENCE
gpostmaster_domains_datas-0.0.3.dist-info/METADATA
gpostmaster_domains_datas-0.0.3.dist-info/WHEEL
gpostmaster_domains_datas-0.0.3.dist-info/entry_points.txt
gpostmaster_domains_datas-0.0.3.dist-info/top_level.txt
gpostmaster_domains_datas-0.0.3.dist-info/RECORD
