Metadata-Version: 2.1
Name: gpostmaster-domains-datas
Version: 0.0.3
Summary: Downloads and flattends datas from Google Postmaster Tools (GPT)
Home-page: https://github.com/Mindbaz/python-gpostmaster-domains-datas
Author: Valentin Henon
Author-email: vhenon@mindbaz.com
License: GPLv3
Keywords: google postmaster tools
Classifier: Programming Language :: Python :: 3.6
Classifier: Programming Language :: Python :: 3.7
Classifier: Programming Language :: Python :: 3.8
Classifier: Programming Language :: Python :: 3.9
Requires-Python: >=3.6
License-File: LICENCE
Requires-Dist: google-api-python-client
Requires-Dist: google-auth-httplib2
Requires-Dist: google-auth-oauthlib
